optimas/__init__.py
optimas/gen_functions.py
optimas/sim_functions.py
optimas/core/__init__.py
optimas/core/evaluation.py
optimas/core/parameter.py
optimas/core/task.py
optimas/core/trial.py
optimas/diagnostics/__init__.py
optimas/diagnostics/exploration_diagnostics.py
optimas/evaluators/__init__.py
optimas/evaluators/base.py
optimas/evaluators/chain_evaluator.py
optimas/evaluators/function_evaluator.py
optimas/evaluators/multitask_evaluator.py
optimas/evaluators/template_evaluator.py
optimas/explorations/__init__.py
optimas/explorations/base.py
optimas/generators/__init__.py
optimas/generators/base.py
optimas/generators/grid_sampling.py
optimas/generators/line_sampling.py
optimas/generators/random_sampling.py
optimas/generators/ax/__init__.py
optimas/generators/ax/base.py
optimas/generators/ax/import_error_dummy_generator.py
optimas/generators/ax/developer/__init__.py
optimas/generators/ax/developer/ax_metric.py
optimas/generators/ax/developer/multitask.py
optimas/generators/ax/service/__init__.py
optimas/generators/ax/service/ax_client.py
optimas/generators/ax/service/base.py
optimas/generators/ax/service/multi_fidelity.py
optimas/generators/ax/service/single_fidelity.py
optimas/utils/__init__.py
optimas/utils/logger.py
optimas/utils/other.py
optimas/utils/ax/__init__.py
optimas/utils/ax/ax_model_manager.py
optimas/utils/ax/other.py
optimas-0.8.1.dist-info/METADATA
optimas-0.8.1.dist-info/WHEEL
optimas-0.8.1.dist-info/top_level.txt
optimas-0.8.1.dist-info/RECORD
