Metadata-Version: 2.4
Name: optimas
Version: 0.8.1
Summary: Optimization at scale, powered by libEnsemble
Author-email: Optimas Developers <angel.ferran.pousa@desy.de>
License: BSD-3-Clause-LBNL
Project-URL: Documentation, https://optimas.readthedocs.io/
Keywords: optimization,scale,bayesian
Classifier: Development Status :: 3 - Alpha
Classifier: Intended Audience :: Science/Research
Classifier: Topic :: Scientific/Engineering
Classifier: Operating System :: OS Independent
Classifier: Programming Language :: Python :: 3.10
Classifier: Programming Language :: Python :: 3.11
Requires-Python: >=3.10
Requires-Dist: libensemble>=1.3.0
Requires-Dist: jinja2
Requires-Dist: pandas
Requires-Dist: mpi4py
Requires-Dist: pydantic>=2.0
Provides-Extra: test
Requires-Dist: flake8; extra == "test"
Requires-Dist: pytest; extra == "test"
Requires-Dist: pytest-mpi; extra == "test"
Requires-Dist: ax-platform<1.0.0,>=0.5.0; extra == "test"
Requires-Dist: matplotlib; extra == "test"
Provides-Extra: all
Requires-Dist: ax-platform<1.0.0,>=0.5.0; extra == "all"
Requires-Dist: matplotlib; extra == "all"
